pycfutils/__init__.py
pycfutils/ctypes.py
pycfutils/exceptions.py
pycfutils/hopa.dll
pycfutils/io.py
pycfutils/miscellaneous.py
pycfutils/network.py
pycfutils/system.py
pycfutils/version.py
pycfutils/gstreamer/__init__.py
pycfutils/gstreamer/registry_access.py
pycfutils/gui/__init__.py
pycfutils/gui/_win/__init__.py
pycfutils/gui/_win/constants.py
pycfutils/gui/effects/__init__.py
pycfutils/gui/effects/_win.py
pycfutils/include/pycfutils/cinterface.h
pycfutils/libs/libcinterface.lib
pycfutils/setup/__init__.py
pycfutils/setup/command/__init__.py
pycfutils/setup/command/build_clibdll.py
pycfutils/setup/command/install_platlib.py
pycfutils/tests/__init__.py
pycfutils/tests/test_ctypes.py
pycfutils/tests/test_gstreamer.py
pycfutils/tests/test_gui.py
pycfutils/tests/test_io.py
pycfutils/tests/test_miscellaneous.py
pycfutils/tests/test_network.py
pycfutils/tests/test_system.py
pycfutils/tools/__init__.py
pycfutils/tools/connect_to_server.py
pycfutils/tools/cpu_stress.py
pycfutils/tools/network_scan.py
pycfutils/tools/start_server.py
pycfutils-2025.5.6.dist-info/LICENSE
pycfutils-2025.5.6.dist-info/METADATA
pycfutils-2025.5.6.dist-info/WHEEL
pycfutils-2025.5.6.dist-info/top_level.txt
pycfutils-2025.5.6.dist-info/RECORD
