Metadata-Version: 2.1
Name: pycfutils
Version: 2025.5.6
Summary: PyCFUtils (Cristi Fati's Utils for Python (&& more)) - a collection of goodies ((cool) scripts / utilities)
Home-page: https://github.com/CristiFati/pycfutils
Download-URL: https://pypi.org/project/pycfutils
Author: Cristi Fati
Author-email: fati_utcluj@yahoo.com
Maintainer: Cristi Fati
Maintainer-email: fati_utcluj@yahoo.com
License: MIT
Platform: All
Classifier: Development Status :: 5 - Production/Stable
Classifier: License :: OSI Approved :: MIT License
Classifier: Operating System :: MacOS
Classifier: Operating System :: Microsoft :: Windows
Classifier: Operating System :: POSIX
Classifier: Operating System :: Unix
Classifier: Programming Language :: C
Classifier: Programming Language :: C++
Classifier: Programming Language :: Python
Classifier: Programming Language :: Python :: 3 :: Only
Classifier: Topic :: Software Development
Classifier: Topic :: Utilities
License-File: LICENSE
